c_func.cpython-312-darwin.so
noisy_bnsp/__init__.py
noisy_bnsp/bigamma.py
noisy_bnsp/nsmodels.py
noisy_bnsp/utils.py
noisy_bnsp/c/c_func.c
noisy_bnsp/c/c_func.pyx
noisy_bnsp/c/c_lib.pxd
noisy_bnsp/c/emp.c
noisy_bnsp/c/emp.h
noisy_bnsp/c/ns_cross_exp.c
noisy_bnsp/c/ns_cross_exp.h
noisy_bnsp/c/ns_cross_gamma.c
noisy_bnsp/c/ns_cross_gamma.h
noisy_bnsp-0.1.0.dist-info/METADATA
noisy_bnsp-0.1.0.dist-info/WHEEL
noisy_bnsp-0.1.0.dist-info/top_level.txt
noisy_bnsp-0.1.0.dist-info/RECORD
