Metadata-Version: 2.1
Name: noisy-bnsp
Version: 0.1.0
Summary: A Python library to simulate and inference on the noisy bivariate Neyman-Scott process.
Author-email: Takaaki Shiotani <shtm.1058@gmail.com>
Project-URL: Homepage, https://github.com/shtmjp/noisy-bnsp
Project-URL: Issues, https://github.com/shtmjp/noisy-bnsp/issues
Keywords: point process,simulation,inference
Classifier: Programming Language :: C
Classifier: Programming Language :: Python :: 3
Requires-Python: >=3.12
Requires-Dist: cython>=3.0.11
Requires-Dist: numpy>=2.2.1
Requires-Dist: scipy>=1.14.1
